LICENSE.txt
MANIFEST.in
README.md
setup.py
jk_uploadpack/Packer.py
jk_uploadpack/SrcFileInfo.py
jk_uploadpack/UPDir.py
jk_uploadpack/UPFile.py
jk_uploadpack/UPFileGroup.py
jk_uploadpack/UPStoredBlob.py
jk_uploadpack/Unpacker.py
jk_uploadpack/__init__.py
jk_uploadpack/helpers.py
jk_uploadpack.egg-info/PKG-INFO
jk_uploadpack.egg-info/SOURCES.txt
jk_uploadpack.egg-info/dependency_links.txt
jk_uploadpack.egg-info/not-zip-safe
jk_uploadpack.egg-info/requires.txt
jk_uploadpack.egg-info/top_level.txt