Metadata-Version: 2.1
Name: jk-uploadpack
Version: 0.2021.3.15
Summary: An archiver based on 'tar' that reduces redundancies before packing.
Home-page: UNKNOWN
Author: Jürgen Knauth
Author-email: pubsrc@binary-overflow.de
License: proprietary
Keywords: archiving,compression,gzip,tar,bzip,xz,webhosting
Platform: UNKNOWN
Classifier: Development Status :: 4 - Beta
Classifier: Programming Language :: Python :: 3
